{"chart":{"chart":{"result":[{"meta":{"currency":"USD","symbol":"CBRS","exchangeName":"NMS","fullExchangeName":"NasdaqGS","instrumentType":"EQUITY","firstTradeDate":1778765400,"regularMarketTime":1780931718,"hasPrePostMarketData":true,"gmtoffset":-14400,"timezone":"EDT","exchangeTimezoneName":"America/New_York","regularMarketPrice":236.21,"fiftyTwoWeekHigh":386.34,"fiftyTwoWeekLow":204.26,"regularMarketDayHigh":239.31,"regularMarketDayLow":204.26,"regularMarketVolume":3822978,"longName":"Cerebras Systems Inc.","shortName":"Cerebras Systems Inc.","chartPreviousClose":350.0,"priceHint":2,"currentTradingPeriod":{"pre":{"timezone":"EDT","start":1780905600,"end":1780925400,"gmtoffset":-14400},"regular":{"timezone":"EDT","start":1780925400,"end":1780948800,"gmtoffset":-14400},"post":{"timezone":"EDT","start":1780948800,"end":1780963200,"gmtoffset":-14400}},"dataGranularity":"1d","range":"2y","validRanges":["1d","5d","1mo","ytd","max"]},"timestamp":[1778765400,1778851800,1779111000,1779197400,1779283800,1779370200,1779456600,1779802200,1779888600,1779975000,1780061400,1780320600,1780407000,1780493400,1780579800,1780666200,1780925400],"indicators":{"quote":[{"close":[311.07000732421875,279.7200012207031,296.6499938964844,303.6300048828125,290.69000244140625,281.8599853515625,256.7799987792969,241.7100067138672,266.8999938964844,242.58999633789062,236.99000549316406,213.27999877929688,236.52000427246094,214.94000244140625,215.39999389648438,201.00999450683594,236.2100067138672],"volume":[33497900,17119200,10158400,10379500,12851700,5448100,11783800,8180300,6523000,5692300,4342400,5823700,5236600,3827700,4137200,4374400,3822978],"high":[386.3399963378906,306.7799987792969,303.6600036621094,333.989990234375,338.3299865722656,294.0,285.0,262.2900085449219,269.3900146484375,268.7799987792969,251.35000610351562,232.3699951171875,241.69000244140625,230.05999755859375,219.77999877929688,222.77999877929688,239.30999755859375],"low":[300.0,275.0,272.239990234375,286.1499938964844,284.25,275.4200134277344,250.27000427246094,236.10000610351562,243.02999877929688,241.52999877929688,232.55999755859375,212.60000610351562,217.0,213.25,205.47000122070312,196.72999572753906,204.25999450683594],"open":[350.0,298.489990234375,291.54998779296875,292.1700134277344,317.5299987792969,293.70001220703125,285.0,260.0,243.86000061035156,260.95001220703125,247.1199951171875,231.8800048828125,220.0500030517578,230.05999755859375,212.25,208.67999267578125,212.99000549316406]}],"adjclose":[{"adjclose":[311.07000732421875,279.7200012207031,296.6499938964844,303.6300048828125,290.69000244140625,281.8599853515625,256.7799987792969,241.7100067138672,266.8999938964844,242.58999633789062,236.99000549316406,213.27999877929688,236.52000427246094,214.94000244140625,215.39999389648438,201.00999450683594,236.2100067138672]}]}}],"error":null}},"combo":null,"news":{"explains":[],"count":10,"quotes":[{"exchange":"NMS","shortname":"Cerebras Systems Inc.","quoteType":"EQUITY","symbol":"CBRS","index":"quotes","score":10024500.0,"typeDisp":"Equity","longname":"Cerebras Systems Inc.","exchDisp":"NASDAQ","sector":"Technology","sectorDisp":"Technology","industry":"Semiconductors","industryDisp":"Semiconductors","dispSecIndFlag":true,"isYahooFinance":true},{"exchange":"PNK","shortname":"Champion Bear Resources Ltd.","quoteType":"EQUITY","symbol":"CBRSF","index":"quotes","score":20005.0,"typeDisp":"Equity","longname":"Champion Bear Resources Ltd.","exchDisp":"OTC Markets","sector":"Basic Materials","sectorDisp":"Basic Materials","industry":"Other Industrial Metals & Mining","industryDisp":"Other Industrial Metals & Mining","isYahooFinance":true},{"exchange":"BTS","shortname":"Tradr 2X Long CBRS Daily ETF","quoteType":"ETF","symbol":"CBRX","index":"quotes","score":20002.0,"typeDisp":"ETF","longname":"Tradr 2X Long CBRS Daily","exchDisp":"BATS Trading","isYahooFinance":true},{"exchange":"BTS","shortname":"Leverage Shares 2X Long CBRS Da","quoteType":"ETF","symbol":"CBRG","index":"quotes","score":20002.0,"typeDisp":"ETF","longname":"Leverage Shares 2X Long CBRS Daily ETF","exchDisp":"BATS Trading","isYahooFinance":true},{"exchange":"CCC","shortname":"Cerebras Systems (Derivatives) USD","quoteType":"CRYPTOCURRENCY","symbol":"CBRS-USD","index":"quotes","score":20001.0,"typeDisp":"Cryptocurrency","longname":"Cerebras Systems (Derivatives) USD","exchDisp":"CCC","isYahooFinance":true},{"exchange":"DUS","shortname":"FTGF-Nasdaq Cybersecurity UE  R","quoteType":"ETF","symbol":"CBRS.DU","index":"quotes","score":20001.0,"typeDisp":"ETF","exchDisp":"Dusseldorf Stock Exchange","isYahooFinance":true},{"exchange":"DXE","shortname":"First Trust Nasdaq Cybersecurit","quoteType":"ETF","symbol":"CBRSD.XD","index":"quotes","score":20001.0,"typeDisp":"ETF","exchDisp":"DXE","isYahooFinance":true}],"news":[{"uuid":"0783108f-9448-307a-8b4c-971987fda50e","title":"Cerebras Likely to Benefit From Low Latency Inference Demand, Morgan Stanley Says","publisher":"MT Newswires","link":"https://finance.yahoo.com/sectors/technology/articles/cerebras-likely-benefit-low-latency-144513230.html","providerPublishTime":1780929913,"type":"STORY","relatedTickers":["CBRS","NVDA"]},{"uuid":"1d05cd45-d499-3e6b-a59b-ce5ae4676f0a","title":"Cerebras initiated, Crocs upgraded: Wall Street's top analyst calls","publisher":"The Fly","link":"https://finance.yahoo.com/news/cvs-upgraded-general-mills-downgraded-135035702.html","providerPublishTime":1780927718,"type":"STORY","thumbnail":{"resolutions":[{"url":"https://s.yimg.com/uu/api/res/1.2/zUit8GQVW5kcaTZHEPMI9Q--~B/aD02Mjg7dz0xMjAwO2FwcGlkPXl0YWNoeW9u/https://media.zenfs.com/en/the_fly_169/5039a5ccc6ec98e1b92bc672330bfcec","width":1200,"height":628,"tag":"original"},{"url":"https://s.yimg.com/uu/api/res/1.2/IPH9wCP.ftudEFOX7xr1MA--~B/Zmk9ZmlsbDtoPTE0MDtweW9mZj0wO3c9MTQwO2FwcGlkPXl0YWNoeW9u/https://media.zenfs.com/en/the_fly_169/5039a5ccc6ec98e1b92bc672330bfcec","width":140,"height":140,"tag":"140x140"}]},"relatedTickers":["CROX","CTSH","RYAN","BXDC","CBT","CBRS","CMI","ALL","ALL-PH","ALL-PI","ALL-PJ","CSR","BXSL","CAR","EMBJ","WRB","KTB","TFX"]},{"uuid":"8f73d55c-b241-3075-81b3-d34e1772fa6d","title":"How Cerebras Stock Can Recover After Sharp Fall Following Its Hot AI Chip IPO","publisher":"Barrons.com","link":"https://finance.yahoo.com/m/8f73d55c-b241-3075-81b3-d34e1772fa6d/how-cerebras-stock-can.html","providerPublishTime":1780926660,"type":"STORY","thumbnail":{"resolutions":[{"url":"https://s.yimg.com/uu/api/res/1.2/O0xpp4nbiJ472Zp205X6AA--~B/aD02NDA7dz0xMjgwO2FwcGlkPXl0YWNoeW9u/https://media.zenfs.com/en/Barrons.com/447b8e5aab979d6cd6db34d0ee7b31b1","width":1280,"height":640,"tag":"original"},{"url":"https://s.yimg.com/uu/api/res/1.2/A58PVb8my.XLQpug2PHWSA--~B/Zmk9ZmlsbDtoPTE0MDtweW9mZj0wO3c9MTQwO2FwcGlkPXl0YWNoeW9u/https://media.zenfs.com/en/Barrons.com/447b8e5aab979d6cd6db34d0ee7b31b1","width":140,"height":140,"tag":"140x140"}]},"relatedTickers":["CBRS"]}],"nav":[],"lists":[],"researchReports":[],"screenerFieldResults":[],"totalTime":69,"timeTakenForQuotes":445,"timeTakenForNews":600,"timeTakenForAlgowatchlist":400,"timeTakenForPredefinedScreener":400,"timeTakenForCrunchbase":0,"timeTakenForNav":400,"timeTakenForResearchReports":0,"timeTakenForScreenerField":0,"timeTakenForCulturalAssets":0,"timeTakenForSearchLists":0},"_fetched":1780931722388}